sim/basics/mux2to1.v
module mux2to1(
	input a,
	input b,
	input sel,
	output out
);
	assign out = sel ? b : a;
endmodule

sim/basics/mux2to1_tb.v
module mux2to1_tb;
	reg a, b, sel;
	wire out;

	mux2to1 uut (.a(a), .b(b), .sel(sel), .out(out));

	initial begin
		$dumpfile("waveform.vcd");
		$dumpvars(0, mux2to1_tb);


		a = 0; b = 0; sel = 0; #10;
		a = 1; b = 0; sel = 0; #10;
		a = 0; b = 1; sel = 0; #10;
		a = 1; b = 1; sel = 0; #10;

		a = 0; b = 0; sel = 1; #10;
                a = 1; b = 0; sel = 1; #10;
                a = 0; b = 1; sel = 1; #10;
                a = 1; b = 1; sel = 1; #10;

		$finish;
	end
endmodule

sim/basics/waveform.vcd
$date
	Mon Sep 21 22:06:41 2026
$end
$version
	Icarus Verilog
$end
$timescale
	1s
$end
$scope module mux2to1_tb $end
$var wire 1 ! out $end
$var reg 1 " a $end
$var reg 1 # b $end
$var reg 1 $ sel $end
$scope module uut $end
$var wire 1 " a $end
$var wire 1 # b $end
$var wire 1 $ sel $end
$var wire 1 ! out $end
$upscope $end
$upscope $end
$enddefinitions $end
$comment Show the parameter values. $end
$dumpall
$end
#0
$dumpvars
0$
0#
0"
0!
$end
#10
1!
1"
#20
0!
1#
0"
#30
1!
1"
#40
0!
1$
0#
0"
#50
1"
#60
1!
1#
0"
#70
1"
